tests/__init__.py
tests/test_yalow.py
yalow/__init__.py
yalow-0.0.2.dist-info/LICENSE
yalow-0.0.2.dist-info/METADATA
yalow-0.0.2.dist-info/WHEEL
yalow-0.0.2.dist-info/top_level.txt
yalow-0.0.2.dist-info/RECORD
