Metadata-Version: 2.1
Name: yalow
Version: 0.0.2
Summary: Yet Another LOgging Wrapper
Home-page: https://github.com/zthurman/yalow
Author: Zechariah Thurman
Author-email: zechariah.thurman@gmail.com
License: UNKNOWN
Platform: UNKNOWN
Classifier: Programming Language :: Python :: 3.7
Classifier: License :: OSI Approved :: Apache Software License
Classifier: Operating System :: OS Independent
Requires-Python: >=3.7
